fyplot/__init__.py
fyplot/dict_plot.py
fyplot/function_plot.py
fyplot-2.1.data/scripts/fyplot_demo
fyplot-2.1.data/scripts/fyplot_demo2
fyplot-2.1.dist-info/LICENSE
fyplot-2.1.dist-info/METADATA
fyplot-2.1.dist-info/WHEEL
fyplot-2.1.dist-info/top_level.txt
fyplot-2.1.dist-info/RECORD
