Metadata-Version: 2.1
Name: fyplot
Version: 2.1
Summary: minimal interface for dynamic time plotting
Home-page: https://github.com/intelligent-soft-robots/fyplot
Author: Vincent Berenz
Author-email: vberenz@tuebingen.mpg.de
License: UNKNOWN
Platform: UNKNOWN
Requires-Dist: pyqtgraph
